{
  "project_info": {
    "project_number": "478751399545",
    "project_id": "flash-chat-5ac4b",
    "storage_bucket": "flash-chat-5ac4b.appspot.com"
  },
  "client": [
    {
      "client_info": {
        "mobilesdk_app_id": "1:478751399545:android:2d2b21fef1feef46cafea8",
        "android_client_info": {
          "package_name": "ucaselabs.com.flashchat"
        }
      },
      "oauth_client": [],
      "api_key": [
        {
          "current_key": "AIzaSyDL71iqOVUwtc0d8n0xUm-pRtPdrzBl7es"
        }
      ],
      "services": {
        "appinvite_service": {
          "other_platform_oauth_client": []
        }
      }
    }
  ],
  "configuration_version": "1"
}